<?xml version="1.0" encoding="utf-8"?>
<Document>
  <Engineering version="V20" />
  <SW.Blocks.InstanceDB ID="0">
    <AttributeList>
      <Access>Published</Access>
      <InstanceOfName>PackedLine.FB_PackedLine</InstanceOfName>
      <InstanceOfType>FB</InstanceOfType>
      <Interface><Sections xmlns="http://www.siemens.com/automation/Openness/SW/Interface/v5">
  <Section Name="Input" />
  <Section Name="Output" />
  <Section Name="InOut" />
  <Section Name="Static">
    <Member Name="G1.1.1" Datatype="&quot;Global.FB_Conveyor&quot;">
      <AttributeList>
        <BooleanAttribute Name="SetPoint" SystemDefined="true">true</BooleanAttribute>
      </AttributeList>
    </Member>
    <Member Name="G1.1.2" Datatype="&quot;Global.FB_Conveyor&quot;">
      <AttributeList>
        <BooleanAttribute Name="SetPoint" SystemDefined="true">true</BooleanAttribute>
      </AttributeList>
    </Member>
    <Member Name="G1.1.3" Datatype="&quot;Global.FB_Conveyor&quot;">
      <AttributeList>
        <BooleanAttribute Name="SetPoint" SystemDefined="true">true</BooleanAttribute>
      </AttributeList>
    </Member>
    <Member Name="G1.1.4" Datatype="&quot;Global.FB_Conveyor&quot;">
      <AttributeList>
        <BooleanAttribute Name="SetPoint" SystemDefined="true">true</BooleanAttribute>
      </AttributeList>
    </Member>
    <Member Name="G1.1.5" Datatype="&quot;Global.FB_Conveyor&quot;">
      <AttributeList>
        <BooleanAttribute Name="SetPoint" SystemDefined="true">true</BooleanAttribute>
      </AttributeList>
    </Member>
    <Member Name="G1.1.6" Datatype="&quot;Global.FB_Conveyor&quot;">
      <AttributeList>
        <BooleanAttribute Name="SetPoint" SystemDefined="true">true</BooleanAttribute>
      </AttributeList>
    </Member>
    <Member Name="G1.1.7" Datatype="&quot;Global.FB_Conveyor&quot;">
      <AttributeList>
        <BooleanAttribute Name="SetPoint" SystemDefined="true">true</BooleanAttribute>
      </AttributeList>
    </Member>
    <Member Name="G1.1.8" Datatype="&quot;Global.FB_Conveyor&quot;">
      <AttributeList>
        <BooleanAttribute Name="SetPoint" SystemDefined="true">true</BooleanAttribute>
      </AttributeList>
    </Member>
    <Member Name="G1.1.9" Datatype="&quot;Global.FB_Conveyor&quot;">
      <AttributeList>
        <BooleanAttribute Name="SetPoint" SystemDefined="true">true</BooleanAttribute>
      </AttributeList>
    </Member>
    <Member Name="G1.1.10" Datatype="&quot;Global.FB_Conveyor&quot;">
      <AttributeList>
        <BooleanAttribute Name="SetPoint" SystemDefined="true">true</BooleanAttribute>
      </AttributeList>
    </Member>
    <Member Name="G1.1.11" Datatype="&quot;Global.FB_Conveyor&quot;">
      <AttributeList>
        <BooleanAttribute Name="SetPoint" SystemDefined="true">true</BooleanAttribute>
      </AttributeList>
    </Member>
    <Member Name="G1.1.12" Datatype="&quot;Global.FB_Conveyor&quot;">
      <AttributeList>
        <BooleanAttribute Name="SetPoint" SystemDefined="true">true</BooleanAttribute>
      </AttributeList>
    </Member>
    <Member Name="G1.1.13" Datatype="&quot;Global.FB_Conveyor&quot;">
      <AttributeList>
        <BooleanAttribute Name="SetPoint" SystemDefined="true">true</BooleanAttribute>
      </AttributeList>
    </Member>
    <Member Name="G1.1.14" Datatype="&quot;Global.FB_Conveyor&quot;">
      <AttributeList>
        <BooleanAttribute Name="SetPoint" SystemDefined="true">true</BooleanAttribute>
      </AttributeList>
    </Member>
    <Member Name="G1.1.15" Datatype="&quot;Global.FB_Conveyor&quot;">
      <AttributeList>
        <BooleanAttribute Name="SetPoint" SystemDefined="true">true</BooleanAttribute>
      </AttributeList>
    </Member>
    <Member Name="G1.1.16" Datatype="&quot;Global.FB_Conveyor&quot;">
      <AttributeList>
        <BooleanAttribute Name="SetPoint" SystemDefined="true">true</BooleanAttribute>
      </AttributeList>
    </Member>
    <Member Name="G1.1.17" Datatype="&quot;Global.FB_Conveyor&quot;">
      <AttributeList>
        <BooleanAttribute Name="SetPoint" SystemDefined="true">true</BooleanAttribute>
      </AttributeList>
    </Member>
    <Member Name="G1.1.18" Datatype="&quot;Global.FB_Conveyor&quot;">
      <AttributeList>
        <BooleanAttribute Name="SetPoint" SystemDefined="true">true</BooleanAttribute>
      </AttributeList>
    </Member>
    <Member Name="G1.1.19" Datatype="&quot;Global.FB_Conveyor&quot;">
      <AttributeList>
        <BooleanAttribute Name="SetPoint" SystemDefined="true">true</BooleanAttribute>
      </AttributeList>
    </Member>
    <Member Name="G1.2.1" Datatype="&quot;Global.FB_Conveyor&quot;">
      <AttributeList>
        <BooleanAttribute Name="SetPoint" SystemDefined="true">true</BooleanAttribute>
      </AttributeList>
    </Member>
    <Member Name="G1.2.2" Datatype="&quot;Global.FB_Conveyor&quot;">
      <AttributeList>
        <BooleanAttribute Name="SetPoint" SystemDefined="true">true</BooleanAttribute>
      </AttributeList>
    </Member>
    <Member Name="G1.3.1" Datatype="&quot;Global.FB_Conveyor&quot;">
      <AttributeList>
        <BooleanAttribute Name="SetPoint" SystemDefined="true">true</BooleanAttribute>
      </AttributeList>
    </Member>
    <Member Name="G1.4.1" Datatype="&quot;Global.FB_Conveyor&quot;">
      <AttributeList>
        <BooleanAttribute Name="SetPoint" SystemDefined="true">true</BooleanAttribute>
      </AttributeList>
    </Member>
    <Member Name="G1.4.2" Datatype="&quot;Global.FB_Conveyor&quot;">
      <AttributeList>
        <BooleanAttribute Name="SetPoint" SystemDefined="true">true</BooleanAttribute>
      </AttributeList>
    </Member>
    <Member Name="G1.4.3" Datatype="&quot;Global.FB_Conveyor&quot;">
      <AttributeList>
        <BooleanAttribute Name="SetPoint" SystemDefined="true">true</BooleanAttribute>
      </AttributeList>
    </Member>
    <Member Name="G1.4.4" Datatype="&quot;Global.FB_Conveyor&quot;">
      <AttributeList>
        <BooleanAttribute Name="SetPoint" SystemDefined="true">true</BooleanAttribute>
      </AttributeList>
    </Member>
    <Member Name="G1.4.5" Datatype="&quot;Global.FB_Conveyor&quot;">
      <AttributeList>
        <BooleanAttribute Name="SetPoint" SystemDefined="true">true</BooleanAttribute>
      </AttributeList>
    </Member>
    <Member Name="G1.4.6" Datatype="&quot;Global.FB_Conveyor&quot;">
      <AttributeList>
        <BooleanAttribute Name="SetPoint" SystemDefined="true">true</BooleanAttribute>
      </AttributeList>
    </Member>
    <Member Name="G1.5.1" Datatype="&quot;Global.FB_Conveyor&quot;">
      <AttributeList>
        <BooleanAttribute Name="SetPoint" SystemDefined="true">true</BooleanAttribute>
      </AttributeList>
    </Member>
    <Member Name="G1.5.2" Datatype="&quot;Global.FB_Conveyor&quot;">
      <AttributeList>
        <BooleanAttribute Name="SetPoint" SystemDefined="true">true</BooleanAttribute>
      </AttributeList>
    </Member>
    <Member Name="G1.5.3" Datatype="&quot;Global.FB_Conveyor&quot;">
      <AttributeList>
        <BooleanAttribute Name="SetPoint" SystemDefined="true">true</BooleanAttribute>
      </AttributeList>
    </Member>
    <Member Name="G1.5.4" Datatype="&quot;Global.FB_Conveyor&quot;">
      <AttributeList>
        <BooleanAttribute Name="SetPoint" SystemDefined="true">true</BooleanAttribute>
      </AttributeList>
    </Member>
    <Member Name="G1.5.5" Datatype="&quot;Global.FB_Conveyor&quot;">
      <AttributeList>
        <BooleanAttribute Name="SetPoint" SystemDefined="true">true</BooleanAttribute>
      </AttributeList>
    </Member>
    <Member Name="G1.5.6" Datatype="&quot;Global.FB_Conveyor&quot;">
      <AttributeList>
        <BooleanAttribute Name="SetPoint" SystemDefined="true">true</BooleanAttribute>
      </AttributeList>
    </Member>
    <Member Name="G1.6.1" Datatype="&quot;Global.FB_Conveyor&quot;">
      <AttributeList>
        <BooleanAttribute Name="SetPoint" SystemDefined="true">true</BooleanAttribute>
      </AttributeList>
    </Member>
    <Member Name="G1.6.2" Datatype="&quot;Global.FB_Conveyor&quot;">
      <AttributeList>
        <BooleanAttribute Name="SetPoint" SystemDefined="true">true</BooleanAttribute>
      </AttributeList>
    </Member>
    <Member Name="G1.7.1" Datatype="&quot;Global.FB_Conveyor&quot;">
      <AttributeList>
        <BooleanAttribute Name="SetPoint" SystemDefined="true">true</BooleanAttribute>
      </AttributeList>
    </Member>
    <Member Name="G1.7.2" Datatype="&quot;Global.FB_Conveyor&quot;">
      <AttributeList>
        <BooleanAttribute Name="SetPoint" SystemDefined="true">true</BooleanAttribute>
      </AttributeList>
    </Member>
    <Member Name="G1.7.3" Datatype="&quot;Global.FB_Conveyor&quot;">
      <AttributeList>
        <BooleanAttribute Name="SetPoint" SystemDefined="true">true</BooleanAttribute>
      </AttributeList>
    </Member>
    <Member Name="G1.7.4" Datatype="&quot;Global.FB_Conveyor&quot;">
      <AttributeList>
        <BooleanAttribute Name="SetPoint" SystemDefined="true">true</BooleanAttribute>
      </AttributeList>
    </Member>
  </Section>
</Sections></Interface>
      <Name>IDB_PackedLine</Name>
      <Namespace>PackedLine</Namespace>
      <Number>10</Number>
      <ProgrammingLanguage>DB</ProgrammingLanguage>
    </AttributeList>
    <ObjectList>
      <MultilingualText ID="1" CompositionName="Comment">
        <ObjectList>
          <MultilingualTextItem ID="2" CompositionName="Items">
            <AttributeList>
              <Culture>cs-CZ</Culture>
              <Text />
            </AttributeList>
          </MultilingualTextItem>
          <MultilingualTextItem ID="3" CompositionName="Items">
            <AttributeList>
              <Culture>en-US</Culture>
              <Text />
            </AttributeList>
          </MultilingualTextItem>
        </ObjectList>
      </MultilingualText>
      <MultilingualText ID="4" CompositionName="Title">
        <ObjectList>
          <MultilingualTextItem ID="5" CompositionName="Items">
            <AttributeList>
              <Culture>cs-CZ</Culture>
              <Text />
            </AttributeList>
          </MultilingualTextItem>
          <MultilingualTextItem ID="6" CompositionName="Items">
            <AttributeList>
              <Culture>en-US</Culture>
              <Text />
            </AttributeList>
          </MultilingualTextItem>
        </ObjectList>
      </MultilingualText>
    </ObjectList>
  </SW.Blocks.InstanceDB>
</Document>